README
setup.cfg
setup.py
Flask_Upwork.egg-info/PKG-INFO
Flask_Upwork.egg-info/SOURCES.txt
Flask_Upwork.egg-info/dependency_links.txt
Flask_Upwork.egg-info/namespace_packages.txt
Flask_Upwork.egg-info/not-zip-safe
Flask_Upwork.egg-info/requires.txt
Flask_Upwork.egg-info/top_level.txt
flaskext/__init__.py
flaskext/odesk.py