Metadata-Version: 1.1
Name: Flask-Upwork
Version: 0.4.1.1
Summary: Upwork API support to Flask
Home-page: https://github.com/strogonoff/flask-upwork
Author: Volodymyr Hotsyk, Anton Strogonoff
Author-email: gotsyk@gmail.com, astrogov@upwork.com
License: BSD
Download-URL: http://github.com/strogonoff/flask-upwork
Platform: any
Classifier: Development Status :: 4 - Beta
Classifier: Environment :: Web Environment
Classifier: Intended Audience :: Developers
Classifier: License :: OSI Approved :: BSD License
Classifier: Operating System :: OS Independent
Classifier: Programming Language :: Python
Classifier: Topic :: Internet :: WWW/HTTP :: Dynamic Content
Classifier: Topic :: Software Development :: Libraries :: Python Modules
